basicsql/__init__.py
basicsql-0.1.5.dist-info/WHEEL
basicsql-0.1.5.dist-info/METADATA
basicsql-0.1.5.dist-info/RECORD
