Metadata-Version: 2.1
Name: basicsql
Version: 0.1.5
Summary: This is a small package intended to help with basic operations such as select, insert, update, and upsert as well as executing raw SQL queries for different database types.
License: MIT
Author: Ramon Brandt
Author-email: devramon22@gmail.com
Requires-Python: >=3.6.1,<4.0.0
Classifier: License :: OSI Approved :: MIT License
Classifier: Programming Language :: Python :: 3
Classifier: Programming Language :: Python :: 3.7
Classifier: Programming Language :: Python :: 3.8
Classifier: Programming Language :: Python :: 3.9
Requires-Dist: jinjasql (>=0.1.7,<0.2.0)
Requires-Dist: numpy (>=1.18.1,<2.0.0)
Requires-Dist: pandas (>=1.0.1,<2.0.0)
Requires-Dist: sqlalchemy (>=1.3.13,<2.0.0)
